LICENSE
MANIFEST.in
README.md
setup.py
qomohub/__init__.py
qomohub/load.py
qomohub/qomolangma.py
qomohub.egg-info/PKG-INFO
qomohub.egg-info/SOURCES.txt
qomohub.egg-info/dependency_links.txt
qomohub.egg-info/requires.txt
qomohub.egg-info/top_level.txt