Metadata-Version: 2.1
Name: qomohub
Version: 0.0.1
Summary: Signal data of Qomolangma (the largest Geoscience Language Model)
Home-page: https://github.com/davendw49/qomolangma-datahub/
Author: Cheng Deng
Author-email: davendw@sjtu.edu.cn
License: Apache
Platform: UNKNOWN
Classifier: License :: OSI Approved :: Apache Software License
Classifier: Operating System :: OS Independent
Classifier: Programming Language :: Python :: 3
Classifier: Programming Language :: Python :: 3.6
Classifier: Programming Language :: Python :: 3.7
Classifier: Programming Language :: Python :: 3.8
Classifier: Programming Language :: Python :: 3.9
Classifier: Topic :: Scientific/Engineering :: Artificial Intelligence
Requires-Python: >=3.7
License-File: LICENSE
